nimbus_scrapy_rabbitmq/__init__.py
nimbus_scrapy_rabbitmq-0.0.3.dist-info/LICENSE.md
nimbus_scrapy_rabbitmq-0.0.3.dist-info/METADATA
nimbus_scrapy_rabbitmq-0.0.3.dist-info/WHEEL
nimbus_scrapy_rabbitmq-0.0.3.dist-info/top_level.txt
nimbus_scrapy_rabbitmq-0.0.3.dist-info/RECORD
